syntia/__init__.py
syntia/app.py
syntia/run.py
syntia/components/__init__.py
syntia/components/horizontal_splitter.py
syntia/components/tabbed_right_panel.py
syntia/components/tabbed_text_area.py
syntia/components/terminal.py
syntia/components/vertical_splitter.py
syntia-0.0.4.dist-info/METADATA
syntia-0.0.4.dist-info/WHEEL
syntia-0.0.4.dist-info/entry_points.txt
syntia-0.0.4.dist-info/licenses/LICENSE
syntia-0.0.4.dist-info/RECORD
